COPYING
MANIFEST.in
README.rst
bootstrap-buildout.py
buildout.cfg
develop.cfg
requirements.txt
setup.py
version.txt
bob/__init__.py
bob.bio.htface.egg-info/PKG-INFO
bob.bio.htface.egg-info/SOURCES.txt
bob.bio.htface.egg-info/dependency_links.txt
bob.bio.htface.egg-info/entry_points.txt
bob.bio.htface.egg-info/not-zip-safe
bob.bio.htface.egg-info/requires.txt
bob.bio.htface.egg-info/top_level.txt
bob/bio/__init__.py
bob/bio/htface/__init__.py
bob/bio/htface/utils.py
bob/bio/htface/algorithm/GFK.py
bob/bio/htface/algorithm/GFK_GaborJet.py
bob/bio/htface/algorithm/GMM_PCA.py
bob/bio/htface/algorithm/HTAlgorithm.py
bob/bio/htface/algorithm/HT_ISOMAP.py
bob/bio/htface/algorithm/HT_LLE.py
bob/bio/htface/algorithm/HT_PCA.py
bob/bio/htface/algorithm/ISV_PCA.py
bob/bio/htface/algorithm/LLE.py
bob/bio/htface/algorithm/LLE_one_modality.py
bob/bio/htface/algorithm/ModalityRegression.py
bob/bio/htface/algorithm/__init__.py
bob/bio/htface/architectures/Transfer.py
bob/bio/htface/architectures/__init__.py
bob/bio/htface/architectures/inception_v1.py
bob/bio/htface/architectures/inception_v1_batch_norm.py
bob/bio/htface/architectures/inception_v2.py
bob/bio/htface/architectures/inception_v2_batch_norm.py
bob/bio/htface/architectures/utils.py
bob/bio/htface/baselines/__init__.py
bob/bio/htface/baselines/inception_v1/__init__.py
bob/bio/htface/baselines/inception_v1/adapt_1_2.py
bob/bio/htface/baselines/inception_v1/adapt_1_4.py
bob/bio/htface/baselines/inception_v1/adapt_1_5.py
bob/bio/htface/baselines/inception_v1/adapt_1_6.py
bob/bio/htface/baselines/inception_v1/adapt_first.py
bob/bio/htface/baselines/inception_v2/__init__.py
bob/bio/htface/baselines/inception_v2/adapt_1_2.py
bob/bio/htface/baselines/inception_v2/adapt_1_4.py
bob/bio/htface/baselines/inception_v2/adapt_1_5.py
bob/bio/htface/baselines/inception_v2/adapt_1_6.py
bob/bio/htface/baselines/inception_v2/adapt_first.py
bob/bio/htface/baselines/sota_baselines/__init__.py
bob/bio/htface/baselines/sota_baselines/isv_baselines.py
bob/bio/htface/baselines/sota_baselines/isv_lbp_baselines.py
bob/bio/htface/baselines/sota_baselines/sota_baselines.py
bob/bio/htface/baselines/standard_facerec/__init__.py
bob/bio/htface/baselines/standard_facerec/standard_facerec.py
